{
  "body": [
    {
      "id": "07700_07793",
      "title": "Egy kun Budán és Pesten",
      "author": "Gubcsi Lajos",
      "lead": "\"Egész életében arról mesél, hogy ő és a népe egyszerre hun, magyar, székely, kun. Ez elég idegesítő, és szemérmetlen módon komolyan is gondolja ezt a történelmietlen kreténséget. Azt hirdeti, hogy nem a történelmi dokumentumok mondják meg elsősorban, hogy ki kicsoda.\"",
      "cover": null,
      "description": "Megtörtént dolgokat ír meg a könyv. Szereplője valóságos személy. Kortárs az ezredfordulón, s előtte fél évszázadon át, Magyarország eme eldurvult életében, melyet a Mohács környéki idők kísértenek közel száz éve egyfolytában, szüntelenül. A valóság leírása színes lett, de a hitelét egyetlen szó sem veszítette el közben. Hősünk legfőbb belső hangja a magabiztos emberi hit, a külső világnak szánt üzenete pedig a hitelesség. A becsület. Mint elementáris követelmény. Író ír egy másikról, aki ő maga: diák, újságíró, közgazdász, igazgató, író és mecénás. S hogy a tisztaság felé terelje lelkiismeretét, fel-felbukkan a könyvben egy, az egész életét végigkísérő beszélgetőpartnere: LELK. Az MP3 formátumú hangmelléklet ismertetője: Gubcsi Lajos 2005-ben írta a Kun Himnuszt, melyet 2006-ban Szabados György zenésített meg. A dal ősbemutatója 2006-ban Gubcsi Lajos Summa című könyvének díszbemutóján volt Karcagon, majd Kiskunfélegyházán, illetve ugyancsak 2006-ban az Ópusztaszeri Nemzeti Történelmi Emlékparkban, ahol először felavatták Gubcsi Lajos adományát, az Őseink nevű szoborpárt, amelyet Györfi Sándor alkotott. A Kun Himnuszt több kórus is feldolgozta és előadta. A jelenlegi változatot Majsai Gábor énekelte fel stúdióban 2011-ben, és amely Gubcsi Lajos Lél nevű legifjabb gyermekének ugyancsak Ópusztaszeren, az Őseinknél tartott keresztelőjén hangzott el először.",
      "audio_files": [],
      "url": "https://mek.oszk.hu/07700/07793"
    },
    {
      "id": "12500_12529",
      "title": "Jut eszembe... ami kimaradt",
      "author": "Gubcsi Lajos",
      "lead": "\"Utólag rájöttem, mennyi szórakoztató, kellemes, tanulságos, néha szomorú momentum maradt ki e beszámolókból. E mostani könyv ezen az arányon hívatott javítani. Megengedem majd magamnak írás közben, hogy ne kövessek világos vonalat a sor- és időrendben. Inkább azon spontán módon jegyezzek le dolgokat, ahogyan azok felmerülnek bennem...\"",
      "cover": null,
      "description": null,
      "audio_files": [
        {
          "url": "01_Ismet_Vereckenel.mp3",
          "title": "01_Ismet_Vereckenel.mp3"
        },
        {
          "url": "02_Ismet_Vereckenel.mp3",
          "title": "02_Ismet_Vereckenel.mp3"
        },
        {
          "url": "03_Ismet_Vereckenel.mp3",
          "title": "03_Ismet_Vereckenel.mp3"
        },
        {
          "url": "04_Ismet_Vereckenel.mp3",
          "title": "04_Ismet_Vereckenel.mp3"
        },
        {
          "url": "05_Ismet_Vereckenel.mp3",
          "title": "05_Ismet_Vereckenel.mp3"
        },
        {
          "url": "06_Ismet_Vereckenel.mp3",
          "title": "06_Ismet_Vereckenel.mp3"
        },
        {
          "url": "07_Ismet_Vereckenel.mp3",
          "title": "07_Ismet_Vereckenel.mp3"
        },
        {
          "url": "08_Ismet_Vereckenel.mp3",
          "title": "08_Ismet_Vereckenel.mp3"
        },
        {
          "url": "09_Ismet_Vereckenel.mp3",
          "title": "09_Ismet_Vereckenel.mp3"
        },
        {
          "url": "10_Ismet_Vereckenel.mp3",
          "title": "10_Ismet_Vereckenel.mp3"
        },
        {
          "url": "11_Ismet_Vereckenel.mp3",
          "title": "11_Ismet_Vereckenel.mp3"
        },
        {
          "url": "12_Ismet_Vereckenel.mp3",
          "title": "12_Ismet_Vereckenel.mp3"
        },
        {
          "url": "13_Ismet_Vereckenel.mp3",
          "title": "13_Ismet_Vereckenel.mp3"
        },
        {
          "url": "14_Ismet_Vereckenel.mp3",
          "title": "14_Ismet_Vereckenel.mp3"
        },
        {
          "url": "15_Ismet_Vereckenel.mp3",
          "title": "15_Ismet_Vereckenel.mp3"
        },
        {
          "url": "16_Ismet_Vereckenel.mp3",
          "title": "16_Ismet_Vereckenel.mp3"
        },
        {
          "url": "17_Ismet_Vereckenel.mp3",
          "title": "17_Ismet_Vereckenel.mp3"
        },
        {
          "url": "18_Ismet_Vereckenel.mp3",
          "title": "18_Ismet_Vereckenel.mp3"
        }
      ],
      "url": "https://mek.oszk.hu/12500/12529"
    },
    {
      "id": "12200_12297",
      "title": "Magyar pokol - 1514",
      "author": "Gubcsi Lajos",
      "lead": "\"Ezt ki lehet heverni, a király és alattvalói háborúja is háború. De itt most nem csak gyilkolás folyt. Itt egyetlen egy nyáron kiölte a magyar a magyart évszázadokra. S ezt ne tudná a török, aki itt áll a határok alatt?! Aki erre vár Nándorfehérvár, 1456 óta, majd Mátyás király halála óta?\"",
      "cover": null,
      "description": null,
      "audio_files": [],
      "url": "https://mek.oszk.hu/12200/12297"
    },
    {
      "id": "02400_02426",
      "title": "Summa",
      "author": "Gubcsi Lajos",
      "lead": "\"A hit tévelyeg, vagy megint az ész a vak Mert nem mertelek, még sose szerettelek A vágy ad-e majd vissza, vagy a gondolat húz mellém e közelre? Add a szívedet...\"",
      "cover": null,
      "description": "A szexust, a szexualitás érzését és tettét, finom erezetét, lágy lányvonalait talán kevesen írták le magyarul olyan árnyaltan és színesen, mint amennyire e könyv. A járdaszegélyre szakadt szegénységet sem sokan. Ha ennyit tettem hozzá a magyar kifejezéshez, megérdemlem az író ember titulust, melyet magamra használok. (G.L.) Az MP3 formátumú hangmelléklet ismertetője: Gubcsi Lajos 2005-ben írta a Kun Himnuszt, melyet 2006-ban Szabados György zenésített meg. A dal ősbemutatója 2006-ban Gubcsi Lajos Summa című könyvének díszbemutóján volt Karcagon, majd Kiskunfélegyházán, illetve ugyancsak 2006-ban az Ópusztaszeri Nemzeti Történelmi Emlékparkban, ahol először felavatták Gubcsi Lajos adományát, az Őseink nevű szoborpárt, amelyet Györfi Sándor alkotott. A Kun Himnuszt több kórus is feldolgozta és előadta. A jelenlegi változatot Majsai Gábor énekelte fel stúdióban 2011-ben, és amely Gubcsi Lajos Lél nevű legifjabb gyermekének ugyancsak Ópusztaszeren, az Őseinknél tartott keresztelőjén hangzott el először.",
      "audio_files": [],
      "url": "https://mek.oszk.hu/02400/02426"
    }
  ]
}