{
  "id": "14600_14695",
  "title": "A zöld anakonda",
  "author": "Barsi Ödön",
  "lead": "\"A falon, az ajtó mellett, egy színes rajz látszott. - Valami kígyót rajzoltak oda - vélte Steve közönyösen. - Oh, jaj! Ez a rettenetes anakonda - tördelte a kezét az anyja. - Anakonda... a mexikói őserdők rettegett óriáskígyója. A mexikóiaknál ez a vérbosszú jele - mondta lassan a sheriff, és hosszan nézett az asszonyra.\"",
  "cover": "/14600/14695/borito.jpg",
  "description": null,
  "audio_files": [
    {
      "url": "01-Bayard_J-A_zold_anakonda.mp3",
      "title": "01-Bayard_J-A_zold_anakonda.mp3 - I. fejezet"
    },
    {
      "url": "02-Bayard_J-A_zold_anakonda.mp3",
      "title": "02-Bayard_J-A_zold_anakonda.mp3 - II. fejezet"
    },
    {
      "url": "03-Bayard_J-A_zold_anakonda.mp3",
      "title": "03-Bayard_J-A_zold_anakonda.mp3 - III. fejezet"
    },
    {
      "url": "04-Bayard_J-A_zold_anakonda.mp3",
      "title": "04-Bayard_J-A_zold_anakonda.mp3 - IV. fejezet"
    },
    {
      "url": "05-Bayard_J-A_zold_anakonda.mp3",
      "title": "05-Bayard_J-A_zold_anakonda.mp3 - V. fejezet"
    },
    {
      "url": "06-Bayard_J-A_zold_anakonda.mp3",
      "title": "06-Bayard_J-A_zold_anakonda.mp3 - VI. fejezet"
    },
    {
      "url": "07-Bayard_J-A_zold_anakonda.mp3",
      "title": "07-Bayard_J-A_zold_anakonda.mp3 - VII. fejezet"
    },
    {
      "url": "08-Bayard_J-A_zold_anakonda.mp3",
      "title": "08-Bayard_J-A_zold_anakonda.mp3 - VIII. fejezet"
    },
    {
      "url": "09-Bayard_J-A_zold_anakonda.mp3",
      "title": "09-Bayard_J-A_zold_anakonda.mp3 - IX. fejezet"
    },
    {
      "url": "10-Bayard_J-A_zold_anakonda.mp3",
      "title": "10-Bayard_J-A_zold_anakonda.mp3 - X. fejezet"
    },
    {
      "url": "11-Bayard_J-A_zold_anakonda.mp3",
      "title": "11-Bayard_J-A_zold_anakonda.mp3 - XI. fejezet"
    }
  ],
  "url": "https://mek.oszk.hu/14600/14695"
}